AsciiLib/AsciiLib.py
AsciiLib/__init__.py
python_AsciiLib-0.0.7.dist-info/METADATA
python_AsciiLib-0.0.7.dist-info/WHEEL
python_AsciiLib-0.0.7.dist-info/top_level.txt
python_AsciiLib-0.0.7.dist-info/RECORD
