Metadata-Version: 2.1
Name: python-AsciiLib
Version: 0.0.7
Summary: An ascii art package
Home-page: https://github.com/HiMeAlex/AsciiLib-Package
Author: Alexander J.
Author-email: alexandergrahambell707@gmail.com
License: MIT
Keywords: ascii
Classifier: Development Status :: 3 - Alpha
Classifier: Intended Audience :: Developers
Classifier: License :: OSI Approved :: MIT License
Classifier: Programming Language :: Python :: 3
Requires-Dist: opencv-python
Requires-Dist: numpy
Requires-Dist: pillow
